supertracker/__init__.py
supertracker/bytetrack/__init__.py
supertracker/bytetrack/core.py
supertracker/bytetrack/kalman_filter.py
supertracker/bytetrack/matching.py
supertracker/bytetrack/single_object_track.py
supertracker/bytetrack/utils.py
supertracker/detection/__init__.py
supertracker/detection/config.py
supertracker/detection/core.py
supertracker/detection/utils.py
supertracker-0.2.0.dist-info/licenses/LICENSE
supertracker-0.2.0.dist-info/METADATA
supertracker-0.2.0.dist-info/WHEEL
supertracker-0.2.0.dist-info/entry_points.txt
supertracker-0.2.0.dist-info/top_level.txt
supertracker-0.2.0.dist-info/RECORD
