Metadata-Version: 2.4
Name: supertracker
Version: 0.2.0
Summary: An easy-to-use library for implementing various multi-object tracking algorithms.
Author-email: Syahvan Alviansyah <syahvanalviansyah91@gmail.com>
License: MIT License
Project-URL: Homepage, https://github.com/Hirai-Labs/supertracker
Keywords: supertracker
Classifier: Intended Audience :: Developers
Classifier: License :: OSI Approved :: MIT License
Classifier: Natural Language :: English
Classifier: Programming Language :: Python :: 3.8
Classifier: Programming Language :: Python :: 3.9
Classifier: Programming Language :: Python :: 3.10
Classifier: Programming Language :: Python :: 3.11
Classifier: Programming Language :: Python :: 3.12
Requires-Python: >=3.8
License-File: LICENSE
Requires-Dist: numpy>=1.20.0
Requires-Dist: pytest>=7.4.3
Requires-Dist: pytest-cov>=4.1.0
Requires-Dist: pytest-xdist>=3.3.1
Requires-Dist: scipy>=1.7.0
Provides-Extra: all
Requires-Dist: supertracker[extra]; extra == "all"
Provides-Extra: dev
Requires-Dist: pytest>=7.0.0; extra == "dev"
Dynamic: license-file
